.gitignore
README.rst
setup.py
django_googlemap_widget.egg-info/PKG-INFO
django_googlemap_widget.egg-info/SOURCES.txt
django_googlemap_widget.egg-info/dependency_links.txt
django_googlemap_widget.egg-info/requires.txt
django_googlemap_widget.egg-info/top_level.txt
django_googlemap_widget.egg-info/zip-safe
googlemap/__init__.py
googlemap/fields.py
googlemap/forms.py
googlemap/models.py
googlemap/types.py
googlemap/widgets.py
googlemap/static/css/django.googlemap.css
googlemap/static/image/django.googlemap.error.png
googlemap/static/image/django.googlemap.hide.png
googlemap/static/image/django.googlemap.loading.gif
googlemap/static/image/django.googlemap.show.png
googlemap/static/image/django.googlemap.submit.png
googlemap/static/javascript/django.googlemap.js
googlemap/templates/googlemap/googlemap.html
googlemap/templates/googlemap/head.html
googlemap/templatetags/__init__.py
googlemap/templatetags/googlemap_tags.py
googlemap_test/sqlite.db
googlemap_test/src/django.wsgi
googlemap_test/src/googlemap_test/__init__.py
googlemap_test/src/googlemap_test/manage.py
googlemap_test/src/googlemap_test/settings.py
googlemap_test/src/googlemap_test/urls.py
googlemap_test/src/googlemap_test/events/__init__.py
googlemap_test/src/googlemap_test/events/admin.py
googlemap_test/src/googlemap_test/events/forms.py
googlemap_test/src/googlemap_test/events/models.py
googlemap_test/src/googlemap_test/events/urls.py
googlemap_test/src/googlemap_test/events/views.py
googlemap_test/src/googlemap_test/events/fixtures/initial_data.json
googlemap_test/static/css/baseline.compress.css
googlemap_test/static/css/layout.css
googlemap_test/static/css/image/Flag.png
googlemap_test/static/css/pepper-grinder/jquery-ui-1.8.5.custom.css
googlemap_test/static/css/pepper-grinder/images/ui-bg_diagonal-maze_20_6e4f1c_10x10.png
googlemap_test/static/css/pepper-grinder/images/ui-bg_diagonal-maze_40_000000_10x10.png
googlemap_test/static/css/pepper-grinder/images/ui-bg_fine-grain_10_eceadf_60x60.png
googlemap_test/static/css/pepper-grinder/images/ui-bg_fine-grain_10_f8f7f6_60x60.png
googlemap_test/static/css/pepper-grinder/images/ui-bg_fine-grain_15_eceadf_60x60.png
googlemap_test/static/css/pepper-grinder/images/ui-bg_fine-grain_15_f7f3de_60x60.png
