Metadata-Version: 1.0
Name: django-googlemap-widget
Version: 0.1.4
Summary: Googlemap field, widget, model for Django
Home-page: https://github.com/lambdalisue/django-googlemap-widget
Author: Alisue
Author-email: lambdalisue@hashnote.net
License: BSD
Download-URL: https://github.com/lambdalisue/django-googlemap-widget/tarball/master
Keywords: django googlemap map ajax
Platform: UNKNOWN
Classifier: Intended Audience :: Developers
Classifier: License :: OSI Approved :: BSD License
Classifier: Programming Language :: Python
Classifier: Topic :: Internet :: WWW/HTTP
